MANIFEST.in
README.md
requirements.txt
setup.py
keras_bi_lm/__init__.py
keras_bi_lm/model.py
keras_bi_lm/weighted_sum.py
keras_bi_lm.egg-info/PKG-INFO
keras_bi_lm.egg-info/SOURCES.txt
keras_bi_lm.egg-info/dependency_links.txt
keras_bi_lm.egg-info/top_level.txt