Metadata-Version: 2.1
Name: keras-bi-lm
Version: 0.25.0
Summary: Train the Bi-LM model and use it as a feature extraction method
Home-page: https://github.com/CyberZHG/keras-bi-lm
Author: CyberZHG
Author-email: CyberZHG@users.noreply.github.com
License: MIT
Platform: UNKNOWN
Classifier: Programming Language :: Python :: 3
Classifier: License :: OSI Approved :: MIT License
Classifier: Operating System :: OS Independent
